pddls/__init__.py
pddls/json2pddl.py
pddls/metricff.py
pddls/pddl2json.py
pddls/pddlsc.py
pddls/yaml2json.py
pddls-0.2.1.data/scripts/json2pddl
pddls-0.2.1.data/scripts/pddl2json
pddls-0.2.1.data/scripts/pddls
pddls-0.2.1.data/scripts/pddlsc
pddls-0.2.1.dist-info/LICENSE
pddls-0.2.1.dist-info/METADATA
pddls-0.2.1.dist-info/WHEEL
pddls-0.2.1.dist-info/top_level.txt
pddls-0.2.1.dist-info/RECORD
