Metadata-Version: 2.1
Name: pddls
Version: 0.2.1
Summary: PDDLS translator package
Home-page: https://github.com/ibm/pddls
Author: Mich Tatsubori
Author-email: mich@jp.ibm.com
License: UNKNOWN
Platform: UNKNOWN
Classifier: Programming Language :: Python :: 3
Classifier: License :: OSI Approved :: MIT License
Classifier: Operating System :: OS Independent
